setup.cfg
setup.py
web2py_utils/__init__.py
web2py_utils/auth_patches.py
web2py_utils/category.py
web2py_utils/configure.py
web2py_utils/db.py
web2py_utils/menu.py
web2py_utils/output.py
web2py_utils/paginate.py
web2py_utils/search.py
web2py_utils/states_years.py
web2py_utils/test_runner.py
web2py_utils/utils.py
web2py_utils/widgets.py
web2py_utils/wordpress2py.py
web2py_utils.egg-info/PKG-INFO
web2py_utils.egg-info/SOURCES.txt
web2py_utils.egg-info/dependency_links.txt
web2py_utils.egg-info/entry_points.txt
web2py_utils.egg-info/not-zip-safe
web2py_utils.egg-info/top_level.txt
web2py_utils/email_sms/__init__.py
web2py_utils/email_sms/carriers.py
web2py_utils/email_sms/db.py
web2py_utils/email_sms/send.py
web2py_utils/py2jquery/__init__.py
web2py_utils/py2jquery/py2jquery.py
web2py_utils/py2jquery/widgets.py