Metadata-Version: 1.0
Name: web2py-utils
Version: 0.0.8dev
Summary: Web2py Utilities
Home-page: http://packages.python.org/web2py_utils/
Author: Thadeus Burgess
Author-email: thadeusb@thadeusb.com
License: GPL v3
Keywords: web2py
Platform: UNKNOWN
Classifier: Development Status :: 3 - Alpha
Classifier: Environment :: Web Environment
Classifier: Intended Audience :: Developers
Classifier: License :: OSI Approved :: GNU General Public License (GPL)
Classifier: Natural Language :: English
Classifier: Programming Language :: Python
Classifier: Topic :: Software Development :: Libraries
Classifier: Topic :: Software Development :: Libraries :: Python Modules
Classifier: Topic :: Utilities
